odoo/addons/invoice_inside_account_menu/README.rst
odoo/addons/invoice_inside_account_menu/__init__.py
odoo/addons/invoice_inside_account_menu/__manifest__.py
odoo/addons/invoice_inside_account_menu/static/description/icon.png
odoo/addons/invoice_inside_account_menu/views/invoicing_in_accouting.xml
odoo_addon_invoice_inside_account_menu-15.0.1.0.0.1.dist-info/METADATA
odoo_addon_invoice_inside_account_menu-15.0.1.0.0.1.dist-info/WHEEL
odoo_addon_invoice_inside_account_menu-15.0.1.0.0.1.dist-info/top_level.txt
odoo_addon_invoice_inside_account_menu-15.0.1.0.0.1.dist-info/RECORD
